qiskit_ibm_catalog/__init__.py
qiskit_ibm_catalog/catalog.py
qiskit_ibm_catalog/serverless.py
qiskit_ibm_catalog-0.10.0.dist-info/LICENSE
qiskit_ibm_catalog-0.10.0.dist-info/LICENSE.txt
qiskit_ibm_catalog-0.10.0.dist-info/METADATA
qiskit_ibm_catalog-0.10.0.dist-info/WHEEL
qiskit_ibm_catalog-0.10.0.dist-info/top_level.txt
qiskit_ibm_catalog-0.10.0.dist-info/RECORD
