Metadata-Version: 2.1
Name: qiskit-ibm-catalog
Version: 0.10.0
License: Copyright 2021 IBM and its contributors
Project-URL: Homepage, https://github.com/Qiskit/qiskit-ibm-catalog
Project-URL: Bug Tracker, https://github.com/Qiskit/qiskit-ibm-catalog/issues
Requires-Python: >=3.9
License-File: LICENSE
License-File: LICENSE.txt
Requires-Dist: certifi>=2021.5.30
Requires-Dist: importlib-metadata>=4.8.1
Requires-Dist: qiskit-serverless~=0.26.0
